missalpha/__init__.py
missalpha/cli.py
missalpha/core.py
missalpha/main.py
missalpha/sample.py
missalpha/data/sample.csv
missalpha-0.1.0.dist-info/LICENSE
missalpha-0.1.0.dist-info/METADATA
missalpha-0.1.0.dist-info/WHEEL
missalpha-0.1.0.dist-info/entry_points.txt
missalpha-0.1.0.dist-info/top_level.txt
missalpha-0.1.0.dist-info/RECORD
